jsonstorage/__init__.py
jsonstorage/exceptions.py
jsonstorage/storage.py
jsonstorage-0.1.0.dist-info/METADATA
jsonstorage-0.1.0.dist-info/WHEEL
jsonstorage-0.1.0.dist-info/top_level.txt
jsonstorage-0.1.0.dist-info/RECORD
