Metadata-Version: 2.1
Name: jsonstorage
Version: 0.1.0
Summary: JSON Storage is a simple lightweight data storage using JSON format in Python.
Home-page: https://github.com/leopires/json_storage
Author: Leonardo Pires
Author-email: lbpires@gmail.com
License: MIT
Platform: UNKNOWN
Classifier: License :: OSI Approved :: MIT License
Classifier: Programming Language :: Python :: 3
Classifier: Programming Language :: Python :: 3.7
